asol_probability_dist/Binomialdistribution.py
asol_probability_dist/Gaussiandistribution.py
asol_probability_dist/Generaldistribution.py
asol_probability_dist/__init__.py
asol_probability_dist-0.2.dist-info/DESCRIPTION.rst
asol_probability_dist-0.2.dist-info/METADATA
asol_probability_dist-0.2.dist-info/RECORD
asol_probability_dist-0.2.dist-info/WHEEL
asol_probability_dist-0.2.dist-info/metadata.json
asol_probability_dist-0.2.dist-info/top_level.txt
