Metadata-Version: 2.0
Name: asol-probability-dist
Version: 0.2
Summary: A package to visualize Gaussian and Binomial probability distributions
Home-page: UNKNOWN
Author: Andrew Leung
Author-email: Andrew.sLeung@gmail.com
License: UNKNOWN
Platform: UNKNOWN
Classifier: Programming Language :: Python :: 3
Classifier: License :: OSI Approved :: MIT License
Classifier: Operating System :: OS Independent
